swara/__init__.py
swara-0.0.1.dist-info/METADATA
swara-0.0.1.dist-info/WHEEL
swara-0.0.1.dist-info/top_level.txt
swara-0.0.1.dist-info/RECORD
