Metadata-Version: 2.4
Name: swara
Version: 0.0.1
Summary: Dummy lock package for swara
Author: AutoPublisher
